{
  "condition": "minecraft:any_of",
  "terms": [
    {
        "condition": "minecraft:location_check",
        "offsetX": 1,
        "offsetZ": -1,
        "predicate": {
          "block": {
            "blocks": "minecraft:campfire",
            "state": {
              "lit": "true",
            "signal_fire": "false"
            }
          }
        }
      },
    {
        "condition": "minecraft:location_check",
        "offsetX": 1,
        "offsetZ": 1,
        "predicate": {
          "block": {
            "blocks": "minecraft:campfire",
            "state": {
              "lit": "true",
            "signal_fire": "false"
            }
          }
        }
      },
    {
        "condition": "minecraft:location_check",
        "offsetX": -1,
        "offsetZ": 1,
        "predicate": {
          "block": {
            "blocks": "minecraft:campfire",
            "state": {
              "lit": "true",
            "signal_fire": "false"
            }
          }
        }
      },
    {
      "condition": "minecraft:location_check",
      "offsetX": 1,
      "offsetZ": -1,
      "predicate": {
        "block": {
          "blocks": "minecraft:campfire",
          "state": {
            "lit": "true",
            "signal_fire": "false"
          }
        }
      }
    },
    {
        "condition": "minecraft:location_check",
        "offsetX": -1,
        "offsetZ": -1,
        "predicate": {
          "block": {
            "blocks": "minecraft:campfire",
            "state": {
              "lit": "true",
            "signal_fire": "false"
            }
          }
        }
      },
    {
        "condition": "minecraft:location_check",
        "offsetZ": -1,
        "predicate": {
          "block": {
            "blocks": "minecraft:campfire",
            "state": {
              "lit": "true",
            "signal_fire": "false"
            }
          }
        }
      },
    {
        "condition": "minecraft:location_check",
        "offsetZ": 1,
        "predicate": {
          "block": {
            "blocks": "minecraft:campfire",
            "state": {
              "lit": "true",
            "signal_fire": "false"
            }
          }
        }
      },
    {
        "condition": "minecraft:location_check",
        "offsetX": -1,
        "predicate": {
          "block": {
            "blocks": "minecraft:campfire",
            "state": {
              "lit": "true",
            "signal_fire": "false"
            }
          }
        }
      },
    {
      "condition": "minecraft:location_check",
      "offsetX": 1,
      "predicate": {
        "block": {
          "blocks": "minecraft:campfire",
          "state": {
            "lit": "true",
            "signal_fire": "false"
          }
        }
      }
    }
  ]
}